epoxy_calc/__init__.py
epoxy_calc-1.1.0.dist-info/METADATA
epoxy_calc-1.1.0.dist-info/WHEEL
epoxy_calc-1.1.0.dist-info/entry_points.txt
epoxy_calc-1.1.0.dist-info/licenses/LICENSE
epoxy_calc-1.1.0.dist-info/RECORD
