Metadata-Version: 2.4
Name: epoxy-calc
Version: 1.1.0
Summary: Swell-resistant epoxy mix calculator
License: GPL-3.0
License-File: LICENSE
Keywords: epoxy,calculator,mixing,resin
Author: Tobias Brox
Author-email: t-epoxy@tobixen.no
Maintainer: Tobias Brox
Maintainer-email: t-epoxy@tobixen.no
Requires-Python: >=3.9
Classifier: Development Status :: 4 - Beta
Classifier: Environment :: Console
Classifier: Intended Audience :: End Users/Desktop
Classifier: License :: OSI Approved :: GNU General Public License v3 or later (GPLv3+)
Classifier: Operating System :: POSIX
Classifier: Programming Language :: Python :: 3
Classifier: Programming Language :: Python :: 3.9
Classifier: Programming Language :: Python :: 3.10
Classifier: Programming Language :: Python :: 3.11
Classifier: Programming Language :: Python :: 3.12
Classifier: Programming Language :: Python :: 3.13
Classifier: Topic :: Utilities
Requires-Dist: Click
Project-URL: Repository, https://github.com/tobixen/epoxy-calc
